<?xml version="1.0" encoding="UTF-8"?>
<beans xmlns="http://www.springframework.org/schema/beans" xmlns:xsi="http://www.w3.org/2001/XMLSchema-instance"
	xmlns:context="http://www.springframework.org/schema/context"
	xsi:schemaLocation="http://www.springframework.org/schema/beans
                                 https://www.springframework.org/schema/beans/spring-beans-2.5.xsd
                                 http://www.springframework.org/schema/context
                                 https://www.springframework.org/schema/context/spring-context-2.5.xsd">

	<bean class="org.springframework.data.hadoop.admin.web.WorkflowMenu" parent="baseMenu"/>
	<bean class="org.springframework.data.hadoop.admin.web.TemplateMenu" parent="baseMenu"/>

	<bean name="redirect:workflows" class="org.springframework.web.servlet.view.RedirectView">
		<property name="url" value="#{resourceService.servletPath}/workflows" />
		<property name="contextRelative" value="true" />
	</bean>

	<bean name="workflows" parent="standard">
		<property name="attributes">
			<props merge="true">
				<prop key="body">/manager/workflows/html/workflows.ftl</prop>
				<prop key="titleCode">workflows.title</prop>
				<prop key="titleText">Spring Hadoop Admin: Workflow Artifacts Uploads</prop>
			</props>
		</property>
	</bean>

	<bean name="workflows.json" parent="standard.json">
		<property name="attributes">
			<props merge="true">
				<prop key="body">/manager/workflows/json/workflows.ftl</prop>
			</props>
		</property>
	</bean>
	
	<bean name="redirect:templates" class="org.springframework.web.servlet.view.RedirectView">
		<property name="url" value="#{resourceService.servletPath}/templates" />
		<property name="contextRelative" value="true" />
	</bean>

	<bean name="templates" parent="standard">
		<property name="attributes">
			<props merge="true">
				<prop key="body">/manager/templates/html/templates.ftl</prop>
				<prop key="titleCode">templates.title</prop>
				<prop key="titleText">Spring Hadoop Admin: Tempalte Management</prop>
			</props>
		</property>
	</bean>

	<bean name="templates.json" parent="standard.json">
		<property name="attributes">
			<props merge="true">
				<prop key="body">/manager/templates/json/templates.ftl</prop>
			</props>
		</property>
	</bean>


</beans>

